{
	"level": 1,
	"regions": [
		{
			"name": "[1-1]",
			"exits": [
				{ 
					"to": "[1-2] Lower",
					"rule": {
						"progressive_warp": {
							"level": 1,
							"count": 1
						}
					}
				}
			]
		},
		{
			"name": "[1-2] Lower",
			"exits": [{ 
				"to": "[1-3]",
				"rule": {
					"and": [
						{
							"progressive_warp": {
								"level": 1,
								"count": 2
							}
						},
						{			
							"weapon_requirement": {
								"location": "Level 1 Start"
							}
						}
					]
				}
			}]
		},
		{
			"name": "[1-3]",
			"exits": [{ 
				"to": "[1-2] Upper",
				"rule": {
					"progressive_warp": {
						"level": 1,
						"count": 3
					}
				}
			}]
		},
		{
			"name": "[1-2] Upper",
			"exits": [{ 
				"to": "[1-4]",
				"rule": {
					"progressive_warp": {
						"level": 1,
						"count": 4
					}
				}
			}]
		},
		{
			"name": "[1-4]",
			"exits": [
				{ "to": "[1-4] Bird Door" },
				{ "to": "[1-4] Upper Primagen Key" },
				{ 
					"to": "[1-5]",
					"rule": {
						"and": [
							{
								"progressive_warp": {
									"level": 1,
									"count": 5
								}
							},
							{				
								"weapon_requirement": {
									"location": "Level 1 Mid"
								}
							}
						]
					}
				}
			]
		},
		{
			"name": "[1-4] Bird Door",
			"exits": []
		},
		{
			"name":  "[1-4] Upper Primagen Key",
			"exits": [
				{ 
					"to": "[1-4] Primagen Key Leap of Faith", 
					"rule": { "has": "Leap of Faith" }
				}
			]
		},
		{
			"name":  "[1-4] Primagen Key Leap of Faith",
			"exits": []
		},
		{
			"name":  "[1-5]",
			"exits": [{ 
				"to": "[1-6]",
				"rule": {
					"progressive_warp": {
						"level": 1,
						"count": 6
					}
				}
			}]
		},
		{
			"name":  "[1-6]",
			"exits": [{ 
				"to": "[1-7]",
				"rule": {
					"progressive_warp": {
						"level": 1,
						"count": 7
					}
				}
			}]
		},
		{
			"name":  "[1-7]",
			"exits": [{ 
				"to": "[1-8]",
				"rule": {
					"progressive_warp": {
						"level": 1,
						"count": 8
					}
				}
			}]
		},
		{
			"name":  "[1-8]",
			"exits": [{ 
				"to": "[1-9]",
				"rule": {
					"and": [
						{
							"progressive_warp": {
								"level": 1,
								"count": 9
							}
						},
						{
							"weapon_requirement": {
								"location": "Level 1 End"
							}
						}
					]
				}
			}]
		},
		{
			"name": "[1-9]",
			"exits": [
				{ "to": "[1-Oblivion]" },
				{
					"to": "[1-Totem]",
					"rule": {
						"mission_item_requirement": {
							"item": "Beacon Power Cell",
							"count": 3
						}
					}
				}
			]
		},
		{
			"name": "[1-Oblivion]",
			"exits": []
		},
		{
			"name": "[1-Totem]",
			"exits": [{ "to": "Hub" }],
			"events": [{
				"name": "Level Complete",
				"location_name": "PoA Complete"
			}]
		}
	]
}